example_data_crawler/__init__.py
example_data_crawler/definitions.py
example_data_crawler/dl_image.py
example_data_crawler/main.py
example_data_crawler-0.1.0.dist-info/METADATA
example_data_crawler-0.1.0.dist-info/WHEEL
example_data_crawler-0.1.0.dist-info/RECORD
