Metadata-Version: 2.1
Name: example_data_crawler
Version: 0.1.0
Summary: 
Author: Foxicution
Author-email: foxicution.dev@gmail.com
Requires-Python: >=3.11,<4.0
Classifier: Programming Language :: Python :: 3
Classifier: Programming Language :: Python :: 3.11
Classifier: Programming Language :: Python :: 3.12
Requires-Dist: lxml (>=4.9.3,<5.0.0)
Requires-Dist: requests (>=2.31.0,<3.0.0)
